promo/__init__.py
promo/duration_morph.py
promo/f0_morph.py
promo/morph_utils/__init__.py
promo/morph_utils/audio_scripts.py
promo/morph_utils/interpolation.py
promo/morph_utils/modify_pitch_accent.py
promo/morph_utils/morph_sequence.py
promo/morph_utils/plot_morphed_data.py
promo/morph_utils/utils.py
promo-2.0.1.dist-info/METADATA
promo-2.0.1.dist-info/WHEEL
promo-2.0.1.dist-info/licenses/LICENSE
promo-2.0.1.dist-info/RECORD
