Metadata-Version: 2.4
Name: promo
Version: 2.0.1
Summary: Library for manipulating pitch and duration in an algorithmic way, for resynthesizing speech
Project-URL: Homepage, https://github.com/timmahrt/ProMo
Author-email: Tim Mahrt <timmahrt@gmail.com>
License: The MIT License (MIT)
License-File: LICENSE
Requires-Python: >=3.6
Requires-Dist: praatio~=6.2.1
Requires-Dist: typing-extensions
